caspometabolism/__init__.py
caspometabolism/__main__.py
caspometabolism/utils.py
caspometabolism-0.1.dist-info/METADATA
caspometabolism-0.1.dist-info/WHEEL
caspometabolism-0.1.dist-info/entry_points.txt
caspometabolism-0.1.dist-info/top_level.txt
caspometabolism-0.1.dist-info/RECORD
